{
  "generated_at": "2026-06-26T23:16:10.784Z",
  "projects": [
    {
      "project": "judkinsparkforpeople",
      "url": "https://judkinsparkforpeople.org",
      "network": "public",
      "current_up": 1,
      "current_status": 200,
      "current_latency_ms": 558,
      "current_error": null,
      "uptime_24h": 100,
      "uptime_7d": 100,
      "uptime_30d": 99.2,
      "incidents_7d": []
    },
    {
      "project": "judkinsparkforpeople-staging",
      "url": "https://judkinsparkforpeople.org/staging/",
      "network": "public",
      "current_up": 1,
      "current_status": 200,
      "current_latency_ms": 377,
      "current_error": null,
      "uptime_24h": 100,
      "uptime_7d": 100,
      "uptime_30d": 100,
      "incidents_7d": []
    },
    {
      "project": "tommyroar-portfolio",
      "url": "https://tommyroar.github.io",
      "network": "public",
      "current_up": 1,
      "current_status": 200,
      "current_latency_ms": 382,
      "current_error": null,
      "uptime_24h": 100,
      "uptime_7d": 100,
      "uptime_30d": 100,
      "incidents_7d": []
    },
    {
      "project": "transit-tracker-web",
      "url": "https://transit-tracker.eastsideurbanism.org/",
      "network": "public",
      "current_up": 1,
      "current_status": 200,
      "current_latency_ms": 441,
      "current_error": null,
      "uptime_24h": 100,
      "uptime_7d": 100,
      "uptime_30d": 100,
      "incidents_7d": []
    },
    {
      "project": "transit-tracker-docs",
      "url": "https://eastsideurbanism.github.io/transit-tracker",
      "network": "public",
      "current_up": 1,
      "current_status": 200,
      "current_latency_ms": 323,
      "current_error": null,
      "uptime_24h": 100,
      "uptime_7d": 100,
      "uptime_30d": 100,
      "incidents_7d": []
    }
  ],
  "incidents_7d": []
}
